Pynacos/Err.py
Pynacos/HoldConfig.py
Pynacos/NacosAdmin.py
Pynacos/NacosConfig.py
Pynacos/NacosInstance.py
Pynacos/NacosService.py
Pynacos/__init__.py
Pynacos/func.py
Pynacos-0.0.2.dist-info/METADATA
Pynacos-0.0.2.dist-info/WHEEL
Pynacos-0.0.2.dist-info/top_level.txt
Pynacos-0.0.2.dist-info/RECORD
