Metadata-Version: 2.1
Name: Pynacos
Version: 0.0.2
Summary: nacos for python
Home-page: https://gitee.com/Martin-word/Pynacos
Author: Martin
Author-email: 1403951401@qq.com
License: UNKNOWN
Platform: UNKNOWN
Classifier: Programming Language :: Python :: 3
Classifier: License :: OSI Approved :: MIT License
Classifier: Operating System :: OS Independent
Requires-Python: >=3.6
Requires-Dist: requests (>=1.0)
